MANIFEST.in
README.md
requirements.txt
setup.py
sick/__init__.py
sick/analysis.py
sick/cli.py
sick/models.py
sick/plot.py
sick/specutils.py
sick/utils.py
sick.egg-info/PKG-INFO
sick.egg-info/SOURCES.txt
sick.egg-info/dependency_links.txt
sick.egg-info/entry_points.txt
sick.egg-info/requires.txt
sick.egg-info/top_level.txt
sick/tests/__init__.py
sick/tests/test_inference.py
sick/tests/test_model.py
sick/tests/test_utils.py