Metadata-Version: 1.0
Name: sick
Version: 0.10
Summary: Infer astrophysical parameters from spectra
Home-page: http://www.github.com/andycasey/sick/
Author: Andrew R. Casey
Author-email: arc@ast.cam.ac.uk
License: MIT
Platform: UNKNOWN
